importgraph.py
importgraph-0.1.dist-info/DESCRIPTION.rst
importgraph-0.1.dist-info/LICENSE.txt
importgraph-0.1.dist-info/METADATA
importgraph-0.1.dist-info/RECORD
importgraph-0.1.dist-info/WHEEL
importgraph-0.1.dist-info/metadata.json
importgraph-0.1.dist-info/top_level.txt
